cachex/__init__.py
cachex/__version__.py
cachex/_core.py
cachex/_hashing.py
cachex/_util.py
cachex/exceptions.py
cachex/factories.py
cachex/ref.py
cachex/value.py
cachex/storage/__init__.py
cachex/storage/base.py
cachex/storage/file.py
cachex/storage/memcached.py
cachex/storage/memory.py
cachex/storage/mongo.py
cachex/storage/redis.py
cachex-0.1.1.dist-info/METADATA
cachex-0.1.1.dist-info/WHEEL
cachex-0.1.1.dist-info/licenses/LICENSE
cachex-0.1.1.dist-info/RECORD
