Metadata-Version: 2.4
Name: cachex
Version: 0.1.1
Summary: Simple, Flexible, and Extensible caching utility for modern applications
Project-URL: Homepage, https://github.com/raid-newvicx/cachex
Project-URL: Source, https://github.com/raid-newvicx/cachex
Author-email: Chris Newville <christopher.newville@raid.dev>
License-Expression: MIT
License-File: LICENSE
Classifier: Development Status :: 4 - Beta
Classifier: Framework :: AsyncIO
Classifier: Intended Audience :: Developers
Classifier: License :: OSI Approved :: MIT License
Classifier: Operating System :: OS Independent
Classifier: Programming Language :: Python :: 3.8
Classifier: Programming Language :: Python :: 3.9
Classifier: Programming Language :: Python :: 3.10
Classifier: Programming Language :: Python :: 3.11
Classifier: Programming Language :: Python :: 3.12
Requires-Python: <4.0,>=3.8
Requires-Dist: anyio
Provides-Extra: mongo
Requires-Dist: motor; extra == 'mongo'
Provides-Extra: redis
Requires-Dist: redis[hiredis]; extra == 'redis'
